[
    {
        "question": "We zoeken een straat: plat water in het frans (Enkel de echte burgie zal dit weten)",
        "hint": "Iets met plat",
        "answer": "Jozef Platteau straat",
        "latitude": 51.045692,
        "longitude": 3.724852
    },
    {
        "question": "We zoeken een straat: plat water in het frans (Enkel de echte burgie zal dit weten) (2)",
        "hint": "Iets met plat",
        "answer": "Jozef Platteau straat",
        "latitude": 51.045692,
        "longitude": 3.724852
    },
    {
        "question": "We zoeken een straat: plat water in het frans (Enkel de echte burgie zal dit weten) (3)",
        "hint": "Iets met plat",
        "answer": "Jozef Platteau straat",
        "latitude": 51.045692,
        "longitude": 3.724852
    },
    {
        "question": "We zoeken een straat: plat water in het frans (Enkel de echte burgie zal dit weten) (4)",
        "hint": "Iets met plat",
        "answer": "Jozef Platteau straat",
        "latitude": 51.045692,
        "longitude": 3.724852
    },
    {
        "question": "We zoeken een straat: plat water in het frans (Enkel de echte burgie zal dit weten) (5)",
        "hint": "Iets met plat",
        "answer": "Jozef Platteau straat",
        "latitude": 51.045692,
        "longitude": 3.724852
    }
]
